{
  "Product": {
    "id": {
      "string": [
        "xXMata_Viejitas2000Xx"  
      ]
    },
    "name": {
      "string": {}
    },
    "description": {
      "string": {}
    },
    "description_short": {
      "string": {}
    },
    "price": {
      "string": {}
    },
    "category": {
      "string": {}
    },
    "img": {
      "string": {}
    },
    "stock": {
      "int": { "min": 0, "max": 1000000 }
    }
  },
  "User": {
    "id": {
      "string": {}
    },
    "fullName": {
      "string": {}
    },
    "username": {
      "string": {}
    },
    "email": {
      "string": {}
    },
    "password": {
      "string": {}
    },
    "telephone": {
      "string": {}
    }
  }
}
